solar_theme/__init__.py
solar_theme/layout.html
solar_theme/theme.conf
solar_theme/static/solar.css
solar_theme/static/solarized-dark.css
solar_theme/static/subtle_dots.png
solar_theme-1.3.3.dist-info/DESCRIPTION.rst
solar_theme-1.3.3.dist-info/METADATA
solar_theme-1.3.3.dist-info/RECORD
solar_theme-1.3.3.dist-info/WHEEL
solar_theme-1.3.3.dist-info/metadata.json
solar_theme-1.3.3.dist-info/top_level.txt
